ctevents/__init__.py
ctevents/ctevents.py
ctevents/gen_events/Event.py
ctevents/gen_events/EventType.py
ctevents/gen_events/ImageDeletedEvent.py
ctevents/gen_events/ImageLabelScore.py
ctevents/gen_events/ImageReceivedEvent.py
ctevents/gen_events/ImageScoredEvent.py
ctevents/gen_events/ImageStoredEvent.py
ctevents/gen_events/NewImageEvent.py
ctevents/gen_events/PluginStartedEvent.py
ctevents/gen_events/PluginTerminateEvent.py
ctevents/gen_events/PluginTerminatingEvent.py
ctevents/gen_events/__init__.py
tapis_ctevents-0.3.1.dist-info/METADATA
tapis_ctevents-0.3.1.dist-info/WHEEL
tapis_ctevents-0.3.1.dist-info/RECORD
